LICENSE
MANIFEST.in
setup.py
twiboozer/__init__.py
twiboozer/formatter.py
twiboozer/markovchain.py
twiboozer/twibot.py
twiboozer.egg-info/PKG-INFO
twiboozer.egg-info/SOURCES.txt
twiboozer.egg-info/dependency_links.txt
twiboozer.egg-info/not-zip-safe
twiboozer.egg-info/requires.txt
twiboozer.egg-info/top_level.txt