Metadata-Version: 1.0
Name: twiboozer
Version: 1.1
Summary: Simple Markov chain text generator integrated with your Twitter account and based on timeline
Home-page: https://github.com/romansalin/twiboozer
Author: Roman Salin
Author-email: romansalin1990@gmail.com
License: UNKNOWN
Keywords: markov chain text generator twitter tweet bot
Platform: UNKNOWN
